ioprocmeta/__init__.py
ioprocmeta/base.py
ioprocmeta/converter.py
ioprocmeta/oep/__init__.py
ioprocmeta/oep/sections.py
ioprocmeta/oep/sectionsv204.py
ioprocmeta-2.2.dist-info/METADATA
ioprocmeta-2.2.dist-info/WHEEL
ioprocmeta-2.2.dist-info/licenses/LICENSE
ioprocmeta-2.2.dist-info/RECORD
