Metadata-Version: 2.3
Name: ioprocmeta
Version: 2.2
Summary: A lightweight library providing an ORM class representing the oep ontology.
Project-URL: homepage, https://gitlab.com/dlr-ve/esy/ioprocmeta
Author-email: Benjamin Fuchs <Benjamin.Fuchs@dlr.de>
Maintainer-email: Benjamin Fuchs <Benjamin.Fuchs@dlr.de>
License: BSD 3-Clause License
Keywords: metadata management,oeo,open energy ontology
Requires-Python: >=3.11
